wack/__init__.py
wack/app.py
wack/cli.py
wack/templates/.gitignore.jinja2
wack/templates/.pre-commit-config.yaml.jinja2
wack/templates/.travis.yml.jinja2
wack/templates/LICENSE.jinja2
wack/templates/setup.py.jinja2
wack/templates/upload.sh.jinja2
wack/templates/wack.py.jinja2
Wack-0.2.0.dist-info/LICENSE.md
Wack-0.2.0.dist-info/METADATA
Wack-0.2.0.dist-info/WHEEL
Wack-0.2.0.dist-info/entry_points.txt
Wack-0.2.0.dist-info/top_level.txt
Wack-0.2.0.dist-info/RECORD
