Metadata-Version: 2.1
Name: Wack
Version: 0.2.0
Summary: A simple CLI and automation tool
Home-page: https://github.com/jackwardell/Wack
Author: Jack Wardell
Author-email: jack@wardell.xyz
License: UNKNOWN
Platform: UNKNOWN
Classifier: Programming Language :: Python :: 3
Classifier: License :: OSI Approved :: MIT License
Classifier: Operating System :: OS Independent
Requires-Python: >=3.6
Requires-Dist: Jinja2 (>=2.10.1)
Requires-Dist: click (>=7)
